.dockerignore
.gitignore
.gitmodules
LICENSE.txt
MANIFEST.in
Makefile
README.md
architecture.dot
architecture.png
population.dot
population.png
setup.cfg
setup.py
.circleci/config.yml
.s2i/environment
docker/dev/docker-compose.yml
docker/prod/docker-compose.yml
docker/prod/nginx/feedback-tool.conf
docker/prod/nginx/nginx.conf
docker/shared/ldif/01-data.ldif
docs/login.png
docs/welcome.png
feedback_tool/__init__.py
feedback_tool/alembic.ini
feedback_tool/config.py
feedback_tool/constants.py
feedback_tool/database.py
feedback_tool/date.py
feedback_tool/example.ini
feedback_tool/forms.py
feedback_tool/history.py
feedback_tool/host_example.ini
feedback_tool/mail.py
feedback_tool/migration.py
feedback_tool/population.py
feedback_tool/stats.py
feedback_tool/text.py
feedback_tool.egg-info/PKG-INFO
feedback_tool.egg-info/SOURCES.txt
feedback_tool.egg-info/dependency_links.txt
feedback_tool.egg-info/entry_points.txt
feedback_tool.egg-info/requires.txt
feedback_tool.egg-info/top_level.txt
feedback_tool/data_migrations/__init__.py
feedback_tool/gunicorn/config.py
feedback_tool/gunicorn/wsgi.py
feedback_tool/migrations/README
feedback_tool/migrations/env.py
feedback_tool/migrations/script.py.mako
feedback_tool/migrations/versions/aa9125020ba8_initial_commit.py
feedback_tool/models/__init__.py
feedback_tool/models/all.py
feedback_tool/models/period.py
feedback_tool/models/user.py
feedback_tool/scripts/__init__.py
feedback_tool/scripts/configure_db.py
feedback_tool/scripts/feedback_app.py
feedback_tool/security/__init__.py
feedback_tool/security/ldapauth.py
feedback_tool/static/assets/favicon-16x16.png
feedback_tool/static/assets/favicon-32x32.png
feedback_tool/static/assets/logo.png
feedback_tool/templates/__init__.py
feedback_tool/templates/email/__init__.py
feedback_tool/templates/email/approve.html.j2
feedback_tool/templates/email/base.html.j2
feedback_tool/templates/email/enrol.html.j2
feedback_tool/templates/email/entry.html.j2
feedback_tool/templates/email/invite.html.j2
feedback_tool/templates/email/review.html.j2
feedback_tool/templates/email/tm_confirmation.html.j2
feedback_tool/views/__init__.py
feedback_tool/views/auth.py
feedback_tool/views/error.py
feedback_tool/views/external.py
