Metadata-Version: 2.1
Name: feedback-tool
Version: 1.0.0
Summary: A platform for managing peer-to-peer feedback within an organisation.
Home-page: https://github.com/manahl/feedback_tool
Author: MAN Alpha Tech
Author-email: ManAlphaTech@man.com
License: GPL 2.0
Download-URL: https://github.com/manahl/feedback_tool/archive/v1.0.0.tar.gz
Keywords: feedback
Platform: UNKNOWN
Classifier: Development Status :: 4 - Beta
Classifier: License :: OSI Approved :: GNU General Public License (GPL)
Classifier: Programming Language :: Python :: 3.7
Classifier: Programming Language :: Python :: 3.6
Classifier: Programming Language :: Python :: 2.7
Provides-Extra: test
Provides-Extra: oracle
Provides-Extra: postgres
